solarmoonpy/__init__.py
solarmoonpy/location.py
solarmoonpy/moon.py
solarmoonpy/sun.py
solarmoonpy/version.py
solarmoonpy-1.0.8.dist-info/licenses/LICENSE
solarmoonpy-1.0.8.dist-info/METADATA
solarmoonpy-1.0.8.dist-info/WHEEL
solarmoonpy-1.0.8.dist-info/top_level.txt
solarmoonpy-1.0.8.dist-info/RECORD
