Metadata-Version: 2.4
Name: solarmoonpy
Version: 1.0.8
Summary: Precise solar and lunar calculations for astronomical applications
Author-email: figorr <jdcuartero@yahoo.es>
License:                                  Apache License
Project-URL: Homepage, https://github.com/figorr/solarmoonpy
Project-URL: Repository, https://github.com/figorr/solarmoonpy.git
Project-URL: Issues, https://github.com/figorr/solarmoonpy/issues
Keywords: astronomy,solar,lunar,sunrise,moonphase,python
Classifier: Development Status :: 4 - Beta
Classifier: Programming Language :: Python :: 3
Classifier: Programming Language :: Python :: 3.10
Classifier: License :: OSI Approved :: Apache Software License
Classifier: Operating System :: OS Independent
Classifier: Topic :: Scientific/Engineering :: Astronomy
Requires-Python: >=3.10
License-File: LICENSE
Dynamic: license-file
